[
{"iso2":"AD","iso3":"AND","ison":"020","fips":"AN","name":"Andorra","cap":"Andorra la Vella","area":468,"pop":84000,"cont":"EU"},
{"iso2":"AE","iso3":"ARE","ison":"784","fips":"AE","name":"United Arab Emirates","cap":"Abu Dhabi","area":82880,"pop":4975593,"cont":"AS"},
{"iso2":"AF","iso3":"AFG","ison":"004","fips":"AF","name":"Afghanistan","cap":"Kabul","area":647500,"pop":29121286,"cont":"AS"},
{"iso2":"AL","iso3":"ALB","ison":"008","fips":"AL","name":"Albania","cap":"Tirana","area":28748,"pop":2986952,"cont":"EU"},
{"iso2":"AM","iso3":"ARM","ison":"051","fips":"AM","name":"Armenia","cap":"Yerevan","area":29800,"pop":2968000,"cont":"AS"},
{"iso2":"AO","iso3":"AGO","ison":"024","fips":"AO","name":"Angola","cap":"Luanda","area":1246700,"pop":13068161,"cont":"AF"},
{"iso2":"AQ","iso3":"ATA","ison":"010","fips":"AY","name":"Antarctica","cap":"","area":14000000,"pop":0,"cont":"AN"},
{"iso2":"AR","iso3":"ARG","ison":"032","fips":"AR","name":"Argentina","cap":"Buenos Aires","area":2766890,"pop":41343201,"cont":"SA"},
{"iso2":"AT","iso3":"AUT","ison":"040","fips":"AU","name":"Austria","cap":"Vienna","area":83858,"pop":8205000,"cont":"EU"},
{"iso2":"AU","iso3":"AUS","ison":"036","fips":"AS","name":"Australia","cap":"Canberra","area":7686850,"pop":21515754,"cont":"OC"},
{"iso2":"AW","iso3":"ABW","ison":"533","fips":"AA","name":"Aruba","cap":"Oranjestad","area":193,"pop":71566,"cont":"NA"},
{"iso2":"AX","iso3":"ALA","ison":"248","fips":"","name":"Åland","cap":"Mariehamn","area":0,"pop":26711,"cont":"EU"},
{"iso2":"AZ","iso3":"AZE","ison":"031","fips":"AJ","name":"Azerbaijan","cap":"Baku","area":86600,"pop":8303512,"cont":"AS"},
{"iso2":"BA","iso3":"BIH","ison":"070","fips":"BK","name":"Bosnia and Herzegovina","cap":"Sarajevo","area":51129,"pop":4590000,"cont":"EU"},
{"iso2":"BD","iso3":"BGD","ison":"050","fips":"BG","name":"Bangladesh","cap":"Dhaka","area":144000,"pop":156118464,"cont":"AS"},
{"iso2":"BE","iso3":"BEL","ison":"056","fips":"BE","name":"Belgium","cap":"Brussels","area":30510,"pop":10403000,"cont":"EU"},
{"iso2":"BF","iso3":"BFA","ison":"854","fips":"UV","name":"Burkina Faso","cap":"Ouagadougou","area":274200,"pop":16241811,"cont":"AF"},
{"iso2":"BG","iso3":"BGR","ison":"100","fips":"BU","name":"Bulgaria","cap":"Sofia","area":110910,"pop":7148785,"cont":"EU"},
{"iso2":"BH","iso3":"BHR","ison":"048","fips":"BA","name":"Bahrain","cap":"Manama","area":665,"pop":738004,"cont":"AS"},
{"iso2":"BI","iso3":"BDI","ison":"108","fips":"BY","name":"Burundi","cap":"Bujumbura","area":27830,"pop":9863117,"cont":"AF"},
{"iso2":"BJ","iso3":"BEN","ison":"204","fips":"BN","name":"Benin","cap":"Porto-Novo","area":112620,"pop":9056010,"cont":"AF"},
{"iso2":"BM","iso3":"BMU","ison":"060","fips":"BD","name":"Bermuda","cap":"Hamilton","area":53,"pop":65365,"cont":"NA"},
{"iso2":"BN","iso3":"BRN","ison":"096","fips":"BX","name":"Brunei","cap":"Bandar Seri Begawan","area":5770,"pop":395027,"cont":"AS"},
{"iso2":"BO","iso3":"BOL","ison":"068","fips":"BL","name":"Bolivia","cap":"Sucre","area":1098580,"pop":9947418,"cont":"SA"},
{"iso2":"BQ","iso3":"BES","ison":"535","fips":"","name":"Bonaire","cap":"Kralendijk","area":294,"pop":18012,"cont":"NA"},
{"iso2":"BR","iso3":"BRA","ison":"076","fips":"BR","name":"Brazil","cap":"Brasilia","area":8511965,"pop":201103330,"cont":"SA"},
{"iso2":"BS","iso3":"BHS","ison":"044","fips":"BF","name":"Bahamas","cap":"Nassau","area":13940,"pop":301790,"cont":"NA"},
{"iso2":"BT","iso3":"BTN","ison":"064","fips":"BT","name":"Bhutan","cap":"Thimphu","area":47000,"pop":699847,"cont":"AS"},
{"iso2":"BW","iso3":"BWA","ison":"072","fips":"BC","name":"Botswana","cap":"Gaborone","area":600370,"pop":2029307,"cont":"AF"},
{"iso2":"BY","iso3":"BLR","ison":"112","fips":"BO","name":"Belarus","cap":"Minsk","area":207600,"pop":9685000,"cont":"EU"},
{"iso2":"BZ","iso3":"BLZ","ison":"084","fips":"BH","name":"Belize","cap":"Belmopan","area":22966,"pop":314522,"cont":"NA"},
{"iso2":"CA","iso3":"CAN","ison":"124","fips":"CA","name":"Canada","cap":"Ottawa","area":9984670,"pop":33679000,"cont":"NA"},
{"iso2":"CC","iso3":"CCK","ison":"166","fips":"CK","name":"Cocos [Keeling] Islands","cap":"West Island","area":14,"pop":628,"cont":"AS"},
{"iso2":"CD","iso3":"COD","ison":"180","fips":"CG","name":"Democratic Republic of the Congo","cap":"Kinshasa","area":2345410,"pop":70916439,"cont":"AF"},
{"iso2":"CF","iso3":"CAF","ison":"140","fips":"CT","name":"Central African Republic","cap":"Bangui","area":622984,"pop":4844927,"cont":"AF"},
{"iso2":"CG","iso3":"COG","ison":"178","fips":"CF","name":"Republic of the Congo","cap":"Brazzaville","area":342000,"pop":3039126,"cont":"AF"},
{"iso2":"CH","iso3":"CHE","ison":"756","fips":"SZ","name":"Switzerland","cap":"Berne","area":41290,"pop":7581000,"cont":"EU"},
{"iso2":"CI","iso3":"CIV","ison":"384","fips":"IV","name":"Ivory Coast","cap":"Yamoussoukro","area":322460,"pop":21058798,"cont":"AF"},
{"iso2":"CK","iso3":"COK","ison":"184","fips":"CW","name":"Cook Islands","cap":"Avarua","area":240,"pop":21388,"cont":"OC"},
{"iso2":"CL","iso3":"CHL","ison":"152","fips":"CI","name":"Chile","cap":"Santiago","area":756950,"pop":16746491,"cont":"SA"},
{"iso2":"CM","iso3":"CMR","ison":"120","fips":"CM","name":"Cameroon","cap":"Yaounde","area":475440,"pop":19294149,"cont":"AF"},
{"iso2":"CN","iso3":"CHN","ison":"156","fips":"CH","name":"China","cap":"Beijing","area":9596960,"pop":1330044000,"cont":"AS"},
{"iso2":"CO","iso3":"COL","ison":"170","fips":"CO","name":"Colombia","cap":"Bogota","area":1138910,"pop":44205293,"cont":"SA"},
{"iso2":"CR","iso3":"CRI","ison":"188","fips":"CS","name":"Costa Rica","cap":"San Jose","area":51100,"pop":4516220,"cont":"NA"},
{"iso2":"CS","iso3":"SCG","ison":"891","fips":"YI","name":"Serbia","cap":"Belgrade","area":102350,"pop":10829175,"cont":"EU"},
{"iso2":"CU","iso3":"CUB","ison":"192","fips":"CU","name":"Cuba","cap":"Havana","area":110860,"pop":11423000,"cont":"NA"},
{"iso2":"CV","iso3":"CPV","ison":"132","fips":"CV","name":"Cape Verde","cap":"Praia","area":4033,"pop":508659,"cont":"AF"},
{"iso2":"CW","iso3":"CUW","ison":"531","fips":"UC","name":"Curaçao","cap":"Willemstad","area":450,"pop":141766,"cont":"NA"},
{"iso2":"CX","iso3":"CXR","ison":"162","fips":"KT","name":"Christmas Island","cap":"Flying Fish Cove","area":135,"pop":1500,"cont":"AS"},
{"iso2":"CY","iso3":"CYP","ison":"196","fips":"CY","name":"Cyprus","cap":"Nicosia","area":9250,"pop":1102677,"cont":"EU"},
{"iso2":"CZ","iso3":"CZE","ison":"203","fips":"EZ","name":"Czechia","cap":"Prague","area":78866,"pop":10476000,"cont":"EU"},
{"iso2":"DE","iso3":"DEU","ison":"276","fips":"GM","name":"Germany","cap":"Berlin","area":357021,"pop":81802257,"cont":"EU"},
{"iso2":"DJ","iso3":"DJI","ison":"262","fips":"DJ","name":"Djibouti","cap":"Djibouti","area":23000,"pop":740528,"cont":"AF"},
{"iso2":"DK","iso3":"DNK","ison":"208","fips":"DA","name":"Denmark","cap":"Copenhagen","area":43094,"pop":5484000,"cont":"EU"},
{"iso2":"DM","iso3":"DMA","ison":"212","fips":"DO","name":"Dominica","cap":"Roseau","area":754,"pop":72813,"cont":"NA"},
{"iso2":"DO","iso3":"DOM","ison":"214","fips":"DR","name":"Dominican Republic","cap":"Santo Domingo","area":48730,"pop":9823821,"cont":"NA"},
{"iso2":"DZ","iso3":"DZA","ison":"012","fips":"AG","name":"Algeria","cap":"Algiers","area":2381740,"pop":34586184,"cont":"AF"},
{"iso2":"EC","iso3":"ECU","ison":"218","fips":"EC","name":"Ecuador","cap":"Quito","area":283560,"pop":14790608,"cont":"SA"},
{"iso2":"EE","iso3":"EST","ison":"233","fips":"EN","name":"Estonia","cap":"Tallinn","area":45226,"pop":1291170,"cont":"EU"},
{"iso2":"EG","iso3":"EGY","ison":"818","fips":"EG","name":"Egypt","cap":"Cairo","area":1001450,"pop":80471869,"cont":"AF"},
{"iso2":"EH","iso3":"ESH","ison":"732","fips":"WI","name":"Western Sahara","cap":"El-Aaiun","area":266000,"pop":273008,"cont":"AF"},
{"iso2":"ER","iso3":"ERI","ison":"232","fips":"ER","name":"Eritrea","cap":"Asmara","area":121320,"pop":5792984,"cont":"AF"},
{"iso2":"ES","iso3":"ESP","ison":"724","fips":"SP","name":"Spain","cap":"Madrid","area":504782,"pop":46505963,"cont":"EU"},
{"iso2":"ET","iso3":"ETH","ison":"231","fips":"ET","name":"Ethiopia","cap":"Addis Ababa","area":1127127,"pop":88013491,"cont":"AF"},
{"iso2":"FI","iso3":"FIN","ison":"246","fips":"FI","name":"Finland","cap":"Helsinki","area":337030,"pop":5244000,"cont":"EU"},
{"iso2":"FJ","iso3":"FJI","ison":"242","fips":"FJ","name":"Fiji","cap":"Suva","area":18270,"pop":875983,"cont":"OC"},
{"iso2":"FK","iso3":"FLK","ison":"238","fips":"FK","name":"Falkland Islands","cap":"Stanley","area":12173,"pop":2638,"cont":"SA"},
{"iso2":"FM","iso3":"FSM","ison":"583","fips":"FM","name":"Micronesia","cap":"Palikir","area":702,"pop":107708,"cont":"OC"},
{"iso2":"FO","iso3":"FRO","ison":"234","fips":"FO","name":"Faroe Islands","cap":"Torshavn","area":1399,"pop":48228,"cont":"EU"},
{"iso2":"FR","iso3":"FRA","ison":"250","fips":"FR","name":"France","cap":"Paris","area":547030,"pop":64768389,"cont":"EU"},
{"iso2":"GA","iso3":"GAB","ison":"266","fips":"GB","name":"Gabon","cap":"Libreville","area":267667,"pop":1545255,"cont":"AF"},
{"iso2":"GB","iso3":"GBR","ison":"826","fips":"UK","name":"United Kingdom","cap":"London","area":244820,"pop":62348447,"cont":"EU"},
{"iso2":"GD","iso3":"GRD","ison":"308","fips":"GJ","name":"Grenada","cap":"St. George's","area":344,"pop":107818,"cont":"NA"},
{"iso2":"GE","iso3":"GEO","ison":"268","fips":"GG","name":"Georgia","cap":"Tbilisi","area":69700,"pop":4630000,"cont":"AS"},
{"iso2":"GH","iso3":"GHA","ison":"288","fips":"GH","name":"Ghana","cap":"Accra","area":239460,"pop":24339838,"cont":"AF"},
{"iso2":"GI","iso3":"GIB","ison":"292","fips":"GI","name":"Gibraltar","cap":"Gibraltar","area":6,"pop":27884,"cont":"EU"},
{"iso2":"GL","iso3":"GRL","ison":"304","fips":"GL","name":"Greenland","cap":"Nuuk","area":2166086,"pop":56375,"cont":"NA"},
{"iso2":"GM","iso3":"GMB","ison":"270","fips":"GA","name":"Gambia","cap":"Banjul","area":11300,"pop":1593256,"cont":"AF"},
{"iso2":"GN","iso3":"GIN","ison":"324","fips":"GV","name":"Guinea","cap":"Conakry","area":245857,"pop":10324025,"cont":"AF"},
{"iso2":"GP","iso3":"GLP","ison":"312","fips":"GP","name":"Guadeloupe","cap":"Basse-Terre","area":1780,"pop":443000,"cont":"NA"},
{"iso2":"GQ","iso3":"GNQ","ison":"226","fips":"EK","name":"Equatorial Guinea","cap":"Malabo","area":28051,"pop":1014999,"cont":"AF"},
{"iso2":"GR","iso3":"GRC","ison":"300","fips":"GR","name":"Greece","cap":"Athens","area":131940,"pop":11000000,"cont":"EU"},
{"iso2":"GT","iso3":"GTM","ison":"320","fips":"GT","name":"Guatemala","cap":"Guatemala City","area":108890,"pop":13550440,"cont":"NA"},
{"iso2":"GU","iso3":"GUM","ison":"316","fips":"GQ","name":"Guam","cap":"Hagatna","area":549,"pop":159358,"cont":"OC"},
{"iso2":"GW","iso3":"GNB","ison":"624","fips":"PU","name":"Guinea-Bissau","cap":"Bissau","area":36120,"pop":1565126,"cont":"AF"},
{"iso2":"GY","iso3":"GUY","ison":"328","fips":"GY","name":"Guyana","cap":"Georgetown","area":214970,"pop":748486,"cont":"SA"},
{"iso2":"HK","iso3":"HKG","ison":"344","fips":"HK","name":"Hong Kong","cap":"Hong Kong","area":1092,"pop":6898686,"cont":"AS"},
{"iso2":"HN","iso3":"HND","ison":"340","fips":"HO","name":"Honduras","cap":"Tegucigalpa","area":112090,"pop":7989415,"cont":"NA"},
{"iso2":"HR","iso3":"HRV","ison":"191","fips":"HR","name":"Croatia","cap":"Zagreb","area":56542,"pop":4491000,"cont":"EU"},
{"iso2":"HT","iso3":"HTI","ison":"332","fips":"HA","name":"Haiti","cap":"Port-au-Prince","area":27750,"pop":9648924,"cont":"NA"},
{"iso2":"HU","iso3":"HUN","ison":"348","fips":"HU","name":"Hungary","cap":"Budapest","area":93030,"pop":9982000,"cont":"EU"},
{"iso2":"ID","iso3":"IDN","ison":"360","fips":"ID","name":"Indonesia","cap":"Jakarta","area":1919440,"pop":242968342,"cont":"AS"},
{"iso2":"IE","iso3":"IRL","ison":"372","fips":"EI","name":"Ireland","cap":"Dublin","area":70280,"pop":4622917,"cont":"EU"},
{"iso2":"IL","iso3":"ISR","ison":"376","fips":"IS","name":"Israel","cap":"Jerusalem","area":20770,"pop":7353985,"cont":"AS"},
{"iso2":"IM","iso3":"IMN","ison":"833","fips":"IM","name":"Isle of Man","cap":"Douglas Isle of Man","area":572,"pop":75049,"cont":"EU"},
{"iso2":"IN","iso3":"IND","ison":"356","fips":"IN","name":"India","cap":"New Delhi","area":3287590,"pop":1173108018,"cont":"AS"},
{"iso2":"IO","iso3":"IOT","ison":"086","fips":"IO","name":"British Indian Ocean Territory","cap":"Diego Garcia","area":60,"pop":4000,"cont":"AS"},
{"iso2":"IQ","iso3":"IRQ","ison":"368","fips":"IZ","name":"Iraq","cap":"Baghdad","area":437072,"pop":29671605,"cont":"AS"},
{"iso2":"IR","iso3":"IRN","ison":"364","fips":"IR","name":"Iran","cap":"Tehran","area":1648000,"pop":76923300,"cont":"AS"},
{"iso2":"IS","iso3":"ISL","ison":"352","fips":"IC","name":"Iceland","cap":"Reykjavik","area":103000,"pop":308910,"cont":"EU"},
{"iso2":"IT","iso3":"ITA","ison":"380","fips":"IT","name":"Italy","cap":"Rome","area":301230,"pop":60340328,"cont":"EU"},
{"iso2":"JM","iso3":"JAM","ison":"388","fips":"JM","name":"Jamaica","cap":"Kingston","area":10991,"pop":2847232,"cont":"NA"},
{"iso2":"JO","iso3":"JOR","ison":"400","fips":"JO","name":"Jordan","cap":"Amman","area":92300,"pop":6407085,"cont":"AS"},
{"iso2":"JP","iso3":"JPN","ison":"392","fips":"JA","name":"Japan","cap":"Tokyo","area":377835,"pop":127288000,"cont":"AS"},
{"iso2":"KE","iso3":"KEN","ison":"404","fips":"KE","name":"Kenya","cap":"Nairobi","area":582650,"pop":40046566,"cont":"AF"},
{"iso2":"KG","iso3":"KGZ","ison":"417","fips":"KG","name":"Kyrgyzstan","cap":"Bishkek","area":198500,"pop":5508626,"cont":"AS"},
{"iso2":"KH","iso3":"KHM","ison":"116","fips":"CB","name":"Cambodia","cap":"Phnom Penh","area":181040,"pop":14453680,"cont":"AS"},
{"iso2":"KI","iso3":"KIR","ison":"296","fips":"KR","name":"Kiribati","cap":"Tarawa","area":811,"pop":92533,"cont":"OC"},
{"iso2":"KM","iso3":"COM","ison":"174","fips":"CN","name":"Comoros","cap":"Moroni","area":2170,"pop":773407,"cont":"AF"},
{"iso2":"KP","iso3":"PRK","ison":"408","fips":"KN","name":"North Korea","cap":"Pyongyang","area":120540,"pop":22912177,"cont":"AS"},
{"iso2":"KR","iso3":"KOR","ison":"410","fips":"KS","name":"South Korea","cap":"Seoul","area":98480,"pop":48422644,"cont":"AS"},
{"iso2":"KW","iso3":"KWT","ison":"414","fips":"KU","name":"Kuwait","cap":"Kuwait City","area":17820,"pop":2789132,"cont":"AS"},
{"iso2":"KY","iso3":"CYM","ison":"136","fips":"CJ","name":"Cayman Islands","cap":"George Town","area":262,"pop":44270,"cont":"NA"},
{"iso2":"KZ","iso3":"KAZ","ison":"398","fips":"KZ","name":"Kazakhstan","cap":"Astana","area":2717300,"pop":15340000,"cont":"AS"},
{"iso2":"LA","iso3":"LAO","ison":"418","fips":"LA","name":"Laos","cap":"Vientiane","area":236800,"pop":6368162,"cont":"AS"},
{"iso2":"LB","iso3":"LBN","ison":"422","fips":"LE","name":"Lebanon","cap":"Beirut","area":10400,"pop":4125247,"cont":"AS"},
{"iso2":"LI","iso3":"LIE","ison":"438","fips":"LS","name":"Liechtenstein","cap":"Vaduz","area":160,"pop":35000,"cont":"EU"},
{"iso2":"LK","iso3":"LKA","ison":"144","fips":"CE","name":"Sri Lanka","cap":"Colombo","area":65610,"pop":21513990,"cont":"AS"},
{"iso2":"LR","iso3":"LBR","ison":"430","fips":"LI","name":"Liberia","cap":"Monrovia","area":111370,"pop":3685076,"cont":"AF"},
{"iso2":"LS","iso3":"LSO","ison":"426","fips":"LT","name":"Lesotho","cap":"Maseru","area":30355,"pop":1919552,"cont":"AF"},
{"iso2":"LT","iso3":"LTU","ison":"440","fips":"LH","name":"Lithuania","cap":"Vilnius","area":65200,"pop":3565000,"cont":"EU"},
{"iso2":"LU","iso3":"LUX","ison":"442","fips":"LU","name":"Luxembourg","cap":"Luxembourg","area":2586,"pop":497538,"cont":"EU"},
{"iso2":"LV","iso3":"LVA","ison":"428","fips":"LG","name":"Latvia","cap":"Riga","area":64589,"pop":2217969,"cont":"EU"},
{"iso2":"LY","iso3":"LBY","ison":"434","fips":"LY","name":"Libya","cap":"Tripolis","area":1759540,"pop":6461454,"cont":"AF"},
{"iso2":"MA","iso3":"MAR","ison":"504","fips":"MO","name":"Morocco","cap":"Rabat","area":446550,"pop":31627428,"cont":"AF"},
{"iso2":"MC","iso3":"MCO","ison":"492","fips":"MN","name":"Monaco","cap":"Monaco","area":2,"pop":32965,"cont":"EU"},
{"iso2":"MD","iso3":"MDA","ison":"498","fips":"MD","name":"Moldova","cap":"Chisinau","area":33843,"pop":4324000,"cont":"EU"},
{"iso2":"ME","iso3":"MNE","ison":"499","fips":"MJ","name":"Montenegro","cap":"Podgorica","area":14026,"pop":666730,"cont":"EU"},
{"iso2":"MF","iso3":"MAF","ison":"663","fips":"RN","name":"Saint Martin","cap":"Marigot","area":53,"pop":35925,"cont":"NA"},
{"iso2":"MG","iso3":"MDG","ison":"450","fips":"MA","name":"Madagascar","cap":"Antananarivo","area":587040,"pop":21281844,"cont":"AF"},
{"iso2":"MH","iso3":"MHL","ison":"584","fips":"RM","name":"Marshall Islands","cap":"Majuro","area":181,"pop":65859,"cont":"OC"},
{"iso2":"MK","iso3":"MKD","ison":"807","fips":"MK","name":"Macedonia","cap":"Skopje","area":25333,"pop":2061000,"cont":"EU"},
{"iso2":"ML","iso3":"MLI","ison":"466","fips":"ML","name":"Mali","cap":"Bamako","area":1240000,"pop":13796354,"cont":"AF"},
{"iso2":"MM","iso3":"MMR","ison":"104","fips":"BM","name":"Myanmar [Burma]","cap":"Nay Pyi Taw","area":678500,"pop":53414374,"cont":"AS"},
{"iso2":"MN","iso3":"MNG","ison":"496","fips":"MG","name":"Mongolia","cap":"Ulan Bator","area":1565000,"pop":3086918,"cont":"AS"},
{"iso2":"MO","iso3":"MAC","ison":"446","fips":"MC","name":"Macao","cap":"Macao","area":254,"pop":449198,"cont":"AS"},
{"iso2":"MP","iso3":"MNP","ison":"580","fips":"CQ","name":"Northern Mariana Islands","cap":"Saipan","area":477,"pop":53883,"cont":"OC"},
{"iso2":"MR","iso3":"MRT","ison":"478","fips":"MR","name":"Mauritania","cap":"Nouakchott","area":1030700,"pop":3205060,"cont":"AF"},
{"iso2":"MS","iso3":"MSR","ison":"500","fips":"MH","name":"Montserrat","cap":"Plymouth","area":102,"pop":9341,"cont":"NA"},
{"iso2":"MT","iso3":"MLT","ison":"470","fips":"MT","name":"Malta","cap":"Valletta","area":316,"pop":403000,"cont":"EU"},
{"iso2":"MU","iso3":"MUS","ison":"480","fips":"MP","name":"Mauritius","cap":"Port Louis","area":2040,"pop":1294104,"cont":"AF"},
{"iso2":"MV","iso3":"MDV","ison":"462","fips":"MV","name":"Maldives","cap":"Male","area":300,"pop":395650,"cont":"AS"},
{"iso2":"MW","iso3":"MWI","ison":"454","fips":"MI","name":"Malawi","cap":"Lilongwe","area":118480,"pop":15447500,"cont":"AF"},
{"iso2":"MX","iso3":"MEX","ison":"484","fips":"MX","name":"Mexico","cap":"Mexico City","area":1972550,"pop":112468855,"cont":"NA"},
{"iso2":"MY","iso3":"MYS","ison":"458","fips":"MY","name":"Malaysia","cap":"Kuala Lumpur","area":329750,"pop":28274729,"cont":"AS"},
{"iso2":"MZ","iso3":"MOZ","ison":"508","fips":"MZ","name":"Mozambique","cap":"Maputo","area":801590,"pop":22061451,"cont":"AF"},
{"iso2":"NA","iso3":"NAM","ison":"516","fips":"WA","name":"Namibia","cap":"Windhoek","area":825418,"pop":2128471,"cont":"AF"},
{"iso2":"NC","iso3":"NCL","ison":"540","fips":"NC","name":"New Caledonia","cap":"Noumea","area":19060,"pop":216494,"cont":"OC"},
{"iso2":"NE","iso3":"NER","ison":"562","fips":"NG","name":"Niger","cap":"Niamey","area":1267000,"pop":15878271,"cont":"AF"},
{"iso2":"NF","iso3":"NFK","ison":"574","fips":"NF","name":"Norfolk Island","cap":"Kingston","area":34,"pop":1828,"cont":"OC"},
{"iso2":"NG","iso3":"NGA","ison":"566","fips":"NI","name":"Nigeria","cap":"Abuja","area":923768,"pop":154000000,"cont":"AF"},
{"iso2":"NI","iso3":"NIC","ison":"558","fips":"NU","name":"Nicaragua","cap":"Managua","area":129494,"pop":5995928,"cont":"NA"},
{"iso2":"NL","iso3":"NLD","ison":"528","fips":"NL","name":"Netherlands","cap":"Amsterdam","area":41526,"pop":16645000,"cont":"EU"},
{"iso2":"NO","iso3":"NOR","ison":"578","fips":"NO","name":"Norway","cap":"Oslo","area":324220,"pop":5009150,"cont":"EU"},
{"iso2":"NP","iso3":"NPL","ison":"524","fips":"NP","name":"Nepal","cap":"Kathmandu","area":140800,"pop":28951852,"cont":"AS"},
{"iso2":"NR","iso3":"NRU","ison":"520","fips":"NR","name":"Nauru","cap":"Yaren","area":21,"pop":10065,"cont":"OC"},
{"iso2":"NU","iso3":"NIU","ison":"570","fips":"NE","name":"Niue","cap":"Alofi","area":260,"pop":2166,"cont":"OC"},
{"iso2":"NZ","iso3":"NZL","ison":"554","fips":"NZ","name":"New Zealand","cap":"Wellington","area":268680,"pop":4252277,"cont":"OC"},
{"iso2":"OM","iso3":"OMN","ison":"512","fips":"MU","name":"Oman","cap":"Muscat","area":212460,"pop":2967717,"cont":"AS"},
{"iso2":"PA","iso3":"PAN","ison":"591","fips":"PM","name":"Panama","cap":"Panama City","area":78200,"pop":3410676,"cont":"NA"},
{"iso2":"PE","iso3":"PER","ison":"604","fips":"PE","name":"Peru","cap":"Lima","area":1285220,"pop":29907003,"cont":"SA"},
{"iso2":"PF","iso3":"PYF","ison":"258","fips":"FP","name":"French Polynesia","cap":"Papeete","area":4167,"pop":270485,"cont":"OC"},
{"iso2":"PG","iso3":"PNG","ison":"598","fips":"PP","name":"Papua New Guinea","cap":"Port Moresby","area":462840,"pop":6064515,"cont":"OC"},
{"iso2":"PH","iso3":"PHL","ison":"608","fips":"RP","name":"Philippines","cap":"Manila","area":300000,"pop":99900177,"cont":"AS"},
{"iso2":"PK","iso3":"PAK","ison":"586","fips":"PK","name":"Pakistan","cap":"Islamabad","area":803940,"pop":184404791,"cont":"AS"},
{"iso2":"PL","iso3":"POL","ison":"616","fips":"PL","name":"Poland","cap":"Warsaw","area":312685,"pop":38500000,"cont":"EU"},
{"iso2":"PN","iso3":"PCN","ison":"612","fips":"PC","name":"Pitcairn Islands","cap":"Adamstown","area":47,"pop":46,"cont":"OC"},
{"iso2":"PR","iso3":"PRI","ison":"630","fips":"RQ","name":"Puerto Rico","cap":"San Juan","area":9104,"pop":3916632,"cont":"NA"},
{"iso2":"PS","iso3":"PSE","ison":"275","fips":"WE","name":"Palestine","cap":"East Jerusalem","area":5970,"pop":3800000,"cont":"AS"},
{"iso2":"PT","iso3":"PRT","ison":"620","fips":"PO","name":"Portugal","cap":"Lisbon","area":92391,"pop":10676000,"cont":"EU"},
{"iso2":"PW","iso3":"PLW","ison":"585","fips":"PS","name":"Palau","cap":"Melekeok","area":458,"pop":19907,"cont":"OC"},
{"iso2":"PY","iso3":"PRY","ison":"600","fips":"PA","name":"Paraguay","cap":"Asuncion","area":406750,"pop":6375830,"cont":"SA"},
{"iso2":"QA","iso3":"QAT","ison":"634","fips":"QA","name":"Qatar","cap":"Doha","area":11437,"pop":840926,"cont":"AS"},
{"iso2":"RE","iso3":"REU","ison":"638","fips":"RE","name":"Réunion","cap":"Saint-Denis","area":2517,"pop":776948,"cont":"AF"},
{"iso2":"RO","iso3":"ROU","ison":"642","fips":"RO","name":"Romania","cap":"Bucharest","area":237500,"pop":21959278,"cont":"EU"},
{"iso2":"RU","iso3":"RUS","ison":"643","fips":"RS","name":"Russia","cap":"Moscow","area":17100000,"pop":140702000,"cont":"EU"},
{"iso2":"RW","iso3":"RWA","ison":"646","fips":"RW","name":"Rwanda","cap":"Kigali","area":26338,"pop":11055976,"cont":"AF"},
{"iso2":"SA","iso3":"SAU","ison":"682","fips":"SA","name":"Saudi Arabia","cap":"Riyadh","area":1960582,"pop":25731776,"cont":"AS"},
{"iso2":"SB","iso3":"SLB","ison":"090","fips":"BP","name":"Solomon Islands","cap":"Honiara","area":28450,"pop":559198,"cont":"OC"},
{"iso2":"SC","iso3":"SYC","ison":"690","fips":"SE","name":"Seychelles","cap":"Victoria","area":455,"pop":88340,"cont":"AF"},
{"iso2":"SD","iso3":"SDN","ison":"729","fips":"SU","name":"Sudan","cap":"Khartoum","area":1861484,"pop":35000000,"cont":"AF"},
{"iso2":"SE","iso3":"SWE","ison":"752","fips":"SW","name":"Sweden","cap":"Stockholm","area":449964,"pop":9555893,"cont":"EU"},
{"iso2":"SG","iso3":"SGP","ison":"702","fips":"SN","name":"Singapore","cap":"Singapur","area":692,"pop":4701069,"cont":"AS"},
{"iso2":"SH","iso3":"SHN","ison":"654","fips":"SH","name":"Saint Helena","cap":"Jamestown","area":410,"pop":7460,"cont":"AF"},
{"iso2":"SI","iso3":"SVN","ison":"705","fips":"SI","name":"Slovenia","cap":"Ljubljana","area":20273,"pop":2007000,"cont":"EU"},
{"iso2":"SJ","iso3":"SJM","ison":"744","fips":"SV","name":"Svalbard and Jan Mayen","cap":"Longyearbyen","area":62049,"pop":2550,"cont":"EU"},
{"iso2":"SK","iso3":"SVK","ison":"703","fips":"LO","name":"Slovakia","cap":"Bratislava","area":48845,"pop":5455000,"cont":"EU"},
{"iso2":"SL","iso3":"SLE","ison":"694","fips":"SL","name":"Sierra Leone","cap":"Freetown","area":71740,"pop":5245695,"cont":"AF"},
{"iso2":"SM","iso3":"SMR","ison":"674","fips":"SM","name":"San Marino","cap":"San Marino","area":61,"pop":31477,"cont":"EU"},
{"iso2":"SN","iso3":"SEN","ison":"686","fips":"SG","name":"Senegal","cap":"Dakar","area":196190,"pop":12323252,"cont":"AF"},
{"iso2":"SO","iso3":"SOM","ison":"706","fips":"SO","name":"Somalia","cap":"Mogadishu","area":637657,"pop":10112453,"cont":"AF"},
{"iso2":"SR","iso3":"SUR","ison":"740","fips":"NS","name":"Suriname","cap":"Paramaribo","area":163270,"pop":492829,"cont":"SA"},
{"iso2":"SS","iso3":"SSD","ison":"728","fips":"OD","name":"South Sudan","cap":"Juba","area":644329,"pop":8260490,"cont":"AF"},
{"iso2":"ST","iso3":"STP","ison":"678","fips":"TP","name":"São Tomé and Príncipe","cap":"Sao Tome","area":1001,"pop":175808,"cont":"AF"},
{"iso2":"SV","iso3":"SLV","ison":"222","fips":"ES","name":"El Salvador","cap":"San Salvador","area":21040,"pop":6052064,"cont":"NA"},
{"iso2":"SY","iso3":"SYR","ison":"760","fips":"SY","name":"Syria","cap":"Damascus","area":185180,"pop":22198110,"cont":"AS"},
{"iso2":"SZ","iso3":"SWZ","ison":"748","fips":"WZ","name":"Swaziland","cap":"Mbabane","area":17363,"pop":1354051,"cont":"AF"},
{"iso2":"TC","iso3":"TCA","ison":"796","fips":"TK","name":"Turks and Caicos Islands","cap":"Cockburn Town","area":430,"pop":20556,"cont":"NA"},
{"iso2":"TD","iso3":"TCD","ison":"148","fips":"CD","name":"Chad","cap":"N'Djamena","area":1284000,"pop":10543464,"cont":"AF"},
{"iso2":"TG","iso3":"TGO","ison":"768","fips":"TO","name":"Togo","cap":"Lome","area":56785,"pop":6587239,"cont":"AF"},
{"iso2":"TH","iso3":"THA","ison":"764","fips":"TH","name":"Thailand","cap":"Bangkok","area":514000,"pop":67089500,"cont":"AS"},
{"iso2":"TJ","iso3":"TJK","ison":"762","fips":"TI","name":"Tajikistan","cap":"Dushanbe","area":143100,"pop":7487489,"cont":"AS"},
{"iso2":"TL","iso3":"TLS","ison":"626","fips":"TT","name":"East Timor","cap":"Dili","area":15007,"pop":1154625,"cont":"OC"},
{"iso2":"TM","iso3":"TKM","ison":"795","fips":"TX","name":"Turkmenistan","cap":"Ashgabat","area":488100,"pop":4940916,"cont":"AS"},
{"iso2":"TN","iso3":"TUN","ison":"788","fips":"TS","name":"Tunisia","cap":"Tunis","area":163610,"pop":10589025,"cont":"AF"},
{"iso2":"TO","iso3":"TON","ison":"776","fips":"TN","name":"Tonga","cap":"Nuku'alofa","area":748,"pop":122580,"cont":"OC"},
{"iso2":"TR","iso3":"TUR","ison":"792","fips":"TU","name":"Turkey","cap":"Ankara","area":780580,"pop":77804122,"cont":"AS"},
{"iso2":"TT","iso3":"TTO","ison":"780","fips":"TD","name":"Trinidad and Tobago","cap":"Port of Spain","area":5128,"pop":1228691,"cont":"NA"},
{"iso2":"TV","iso3":"TUV","ison":"798","fips":"TV","name":"Tuvalu","cap":"Funafuti","area":26,"pop":10472,"cont":"OC"},
{"iso2":"TW","iso3":"TWN","ison":"158","fips":"TW","name":"Taiwan","cap":"Taipei","area":35980,"pop":22894384,"cont":"AS"},
{"iso2":"TZ","iso3":"TZA","ison":"834","fips":"TZ","name":"Tanzania","cap":"Dodoma","area":945087,"pop":41892895,"cont":"AF"},
{"iso2":"UA","iso3":"UKR","ison":"804","fips":"UP","name":"Ukraine","cap":"Kiev","area":603700,"pop":45415596,"cont":"EU"},
{"iso2":"UG","iso3":"UGA","ison":"800","fips":"UG","name":"Uganda","cap":"Kampala","area":236040,"pop":33398682,"cont":"AF"},
{"iso2":"US","iso3":"USA","ison":"840","fips":"US","name":"United States","cap":"Washington","area":9629091,"pop":310232863,"cont":"NA"},
{"iso2":"UY","iso3":"URY","ison":"858","fips":"UY","name":"Uruguay","cap":"Montevideo","area":176220,"pop":3477000,"cont":"SA"},
{"iso2":"UZ","iso3":"UZB","ison":"860","fips":"UZ","name":"Uzbekistan","cap":"Tashkent","area":447400,"pop":27865738,"cont":"AS"},
{"iso2":"VA","iso3":"VAT","ison":"336","fips":"VT","name":"Vatican City","cap":"Vatican City","area":1,"pop":921,"cont":"EU"},
{"iso2":"VC","iso3":"VCT","ison":"670","fips":"VC","name":"Saint Vincent and the Grenadines","cap":"Kingstown","area":389,"pop":104217,"cont":"NA"},
{"iso2":"VE","iso3":"VEN","ison":"862","fips":"VE","name":"Venezuela","cap":"Caracas","area":912050,"pop":27223228,"cont":"SA"},
{"iso2":"VN","iso3":"VNM","ison":"704","fips":"VM","name":"Vietnam","cap":"Hanoi","area":329560,"pop":89571130,"cont":"AS"},
{"iso2":"VU","iso3":"VUT","ison":"548","fips":"NH","name":"Vanuatu","cap":"Port Vila","area":12200,"pop":221552,"cont":"OC"},
{"iso2":"WF","iso3":"WLF","ison":"876","fips":"WF","name":"Wallis and Futuna","cap":"Mata Utu","area":274,"pop":16025,"cont":"OC"},
{"iso2":"WS","iso3":"WSM","ison":"882","fips":"WS","name":"Samoa","cap":"Apia","area":2944,"pop":192001,"cont":"OC"},
{"iso2":"XK","iso3":"XKX","ison":"0","fips":"KV","name":"Kosovo","cap":"Pristina","area":10908,"pop":1800000,"cont":"EU"},
{"iso2":"YE","iso3":"YEM","ison":"887","fips":"YM","name":"Yemen","cap":"Sanaa","area":527970,"pop":23495361,"cont":"AS"},
{"iso2":"YT","iso3":"MYT","ison":"175","fips":"MF","name":"Mayotte","cap":"Mamoudzou","area":374,"pop":159042,"cont":"AF"},
{"iso2":"ZA","iso3":"ZAF","ison":"710","fips":"SF","name":"South Africa","cap":"Pretoria","area":1219912,"pop":49000000,"cont":"AF"},
{"iso2":"ZM","iso3":"ZMB","ison":"894","fips":"ZA","name":"Zambia","cap":"Lusaka","area":752614,"pop":13460305,"cont":"AF"},
{"iso2":"ZW","iso3":"ZWE","ison":"716","fips":"ZI","name":"Zimbabwe","cap":"Harare","area":390580,"pop":11651858,"cont":"AF"}
]
